{
    "CommandId": "fe083ada-13de-4871-8abf-4fcd5c5b76eb",
    "InstanceId": "i-0335b8c303baaaee0",
    "Comment": "",
    "DocumentName": "AWS-RunShellScript",
    "DocumentVersion": "$DEFAULT",
    "PluginName": "aws:runShellScript",
    "ResponseCode": 0,
    "ExecutionStartDateTime": "2026-03-11T18:31:12.203Z",
    "ExecutionElapsedTime": "PT0.008S",
    "ExecutionEndDateTime": "2026-03-11T18:31:12.203Z",
    "Status": "Success",
    "StatusDetails": "Success",
    "StandardOutputContent": "psql (PostgreSQL) 17.7\n",
    "StandardOutputUrl": "",
    "StandardErrorContent": "",
    "StandardErrorUrl": "",
    "CloudWatchOutputConfig": {
        "CloudWatchLogGroupName": "",
        "CloudWatchOutputEnabled": false
    }
}
