{
    "ListenerArn": "arn:aws:elasticloadbalancing:ap-southeast-1:194442925745:listener/app/budolEcosystem-ALB-production/d9c7d4f568494930/803b5d6a45ef986c",
    "Priority": 102,
    "Conditions": [
        {
            "Field": "path-pattern",
            "PathPatternConfig": {
                "Values": [
                    "/payment/*"
                ]
            }
        }
    ],
    "Actions": [
        {
            "Type": "forward",
            "TargetGroupArn": "arn:aws:elasticloadbalancing:ap-southeast-1:194442925745:targetgroup/budolPayPayment-tg/5b2f2dc80ebd3464"
        }
    ]
}